[
  {
    "name": "Abusive Sergeant",
    "type": "Minion",
    "cost": 1,
    "attack": 1,
    "health": 1,
    "minion_type": null,
    "text": "<b>Battlecry:</b> Give a minion +2_Attack this turn.",
    "img": "http://media.services.zam.com/v1/media/byName/hs/cards/enus/CS2_188.png",
    "imgGold": "http://media.services.zam.com/v1/media/byName/hs/cards/enus/animated/CS2_188_premium.gif",
    "abilities": [
      {
        "name": "add_specs_to_own_minion_for_turn",
        "function": "add_specs_to_own_minion_for_turn",
        "kwargs": {"health": 0, "attack": 2}
      }
    ]
  },
  {
    "name": "Argent Squire",
    "type": "Minion",
    "cost": 1,
    "attack": 1,
    "health": 1,
    "minion_type": null,
    "text": "<b>Divine Shield</b>",
    "img": "http://media.services.zam.com/v1/media/byName/hs/cards/enus/EX1_008.png",
    "imgGold": "http://media.services.zam.com/v1/media/byName/hs/cards/enus/animated/EX1_008_premium.gif",
    "abilities": [
      {
        "name": "divine_shield",
        "function": "divine_shield",
        "kwargs": {}
      }
    ]
  },
  {
    "name": "Divine Strength",
    "type": "Spell",
    "cost": 1,
    "text": "Give a minion +1/+2.",
    "playerClass": "Paladin",
    "img": "http://media.services.zam.com/v1/media/byName/hs/cards/enus/OG_223.png",
    "imgGold": "http://media.services.zam.com/v1/media/byName/hs/cards/enus/animated/OG_223_premium.gif",
    "abilities": [
      {
        "name": "add_specs_to_own_minion",
        "function": "add_specs_to_own_minion",
        "kwargs": {"health": 1, "attack": 2}
      }
    ]
  },
  {
    "name": "Selfless Hero",
    "type": "Minion",
    "cost": 1,
    "attack": 2,
    "health": 1,
    "minion_type": null,
    "text": "<b>Deathrattle:</b> Give a random friendly minion <b>Divine Shield</b>.",
    "playerClass": "Paladin",
    "img": "http://media.services.zam.com/v1/media/byName/hs/cards/enus/OG_221.png",
    "imgGold": "http://media.services.zam.com/v1/media/byName/hs/cards/enus/animated/OG_221_premium.gif",
    "abilities": [
      {
        "name": "deathrattle",
        "function": "add_shield_to_own_minion",
        "kwargs": {}
      }
    ]
  },
  {
    "name": "Divine Favor",
    "type": "Spell",
    "cost": 3,
    "text": "Draw cards until you have as many in hand as your opponent.",
    "playerClass": "Paladin",
    "img": "http://media.services.zam.com/v1/media/byName/hs/cards/enus/EX1_349.png",
    "imgGold": "http://media.services.zam.com/v1/media/byName/hs/cards/enus/animated/EX1_349_premium.gif",
    "abilities": [
      {
        "name": "draw_cards_to_match_opponent",
        "function": "draw_cards_to_match_opponent",
        "kwargs": {}
      }
    ]
  },
  {
    "name": "Seal of Champions",
    "type": "Spell",
    "cost": 3,
    "text": "Give a minion +3 Attack and <b>Divine Shield</b>.",
    "playerClass": "Paladin",
    "img": "http://media.services.zam.com/v1/media/byName/hs/cards/enus/AT_074.png",
    "imgGold": "http://media.services.zam.com/v1/media/byName/hs/cards/enus/animated/AT_074_premium.gif",
    "abilities": [
      {
        "name": "add_divine_shield_and_specs_to_own_minion",
        "function": "add_divine_shield_and_specs_to_own_minion",
        "kwargs": {"health": 3, "attack": 0}
      }
    ]
  },
  {
    "name": "Steward of Darkshire",
    "type": "Minion",
    "cost": 3,
    "attack": 3,
    "health": 3,
    "minion_type": null,
    "text": "<b>Divine Shield</b>.",
    "playerClass": "Paladin",
    "img": "http://media.services.zam.com/v1/media/byName/hs/cards/enus/OG_310.png",
    "imgGold": "http://media.services.zam.com/v1/media/byName/hs/cards/enus/animated/OG_310_premium.gif",
    "abilities": [
      {
        "name": "divine_shield",
        "function": "divine_shield",
        "kwargs": {}
      }
    ]
  },
  {
    "cardId": "CS2_124",
    "dbfId": "289",
    "name": "Wolfrider",
    "cardSet": "Basic",
    "type": "Minion",
    "faction": "Horde",
    "rarity": "Free",
    "cost": 3,
    "attack": 3,
    "health": 1,
    "minion_type": null,
    "text": "<b>Charge</b>",
    "flavor": "Orcish raiders ride wolves because they are well adapted to harsh environments, and because they are soft and cuddly.",
    "artist": "Dany Orizio",
    "collectible": true,
    "playerClass": "Neutral",
    "howToGetGold": "Unlocked at Warrior Level 59.",
    "img": "http://media.services.zam.com/v1/media/byName/hs/cards/enus/CS2_124.png",
    "imgGold": "http://media.services.zam.com/v1/media/byName/hs/cards/enus/animated/CS2_124_premium.gif",
    "locale": "enUS",
    "abilities": [
      {
        "name": "charge",
        "function": "charge",
        "kwargs": {}
      }
    ]
  },
  {
    "name": "Blessing of Kings",
    "type": "Spell",
    "cost": 4,
    "text": "Give a minion +4/+4. <i>(+4 Attack/+4 Health)</i>",
    "playerClass": "Paladin",
    "img": "http://media.services.zam.com/v1/media/byName/hs/cards/enus/CS2_092.png",
    "imgGold": "http://media.services.zam.com/v1/media/byName/hs/cards/enus/animated/CS2_092_premium.gif",
    "abilities": [
      {
        "name": "add_specs_to_own_minion_for_turn",
        "function": "add_specs_to_own_minion_for_turn",
        "kwargs": {"health": 4, "attack": 4}
      }
    ]
  },
  {
    "name": "Defender of Argus",
    "type": "Minion",
    "cost": 4,
    "attack": 2,
    "health": 3,
    "minion_type": null,
    "text": "<b>Battlecry:</b> Give your two random minions +1/+1 and <b>Taunt</b>.",
    "playerClass": "Neutral",
    "img": "http://media.services.zam.com/v1/media/byName/hs/cards/enus/EX1_093.png",
    "imgGold": "http://media.services.zam.com/v1/media/byName/hs/cards/enus/animated/EX1_093_premium.gif",
    "abilities": [
      {
        "name": "add_taunt_shield_and_specs_to_own_minion",
        "function": "add_divine_shield_and_specs_to_own_minion",
        "kwargs": {"health": 1, "attack": 1}
      }
    ]
  }
]